microAO/__init__.py
microAO/aoAlg.py
microAO/aoDev.py
microAO/aoMetrics.py
microAO/config.py
microAO/full_image_stack_zernike_test.py
microAO/non_square_image_test.py
microAO/testsuite/__init__.py
microAO/testsuite/test_functions.py
microscope_aotools-1.1.4.dist-info/COPYING
microscope_aotools-1.1.4.dist-info/METADATA
microscope_aotools-1.1.4.dist-info/WHEEL
microscope_aotools-1.1.4.dist-info/top_level.txt
microscope_aotools-1.1.4.dist-info/RECORD
