Metadata-Version: 2.1
Name: microscope-aotools
Version: 1.1.4
Summary: An extensible microscope adaptive optics use.
Home-page: https://github.com/MicronOxford/microscope-aotools
Author: Nicholas Hall <nicholas.hall@dtc.ox.ac.uk>
License: GPL-3.0+
Platform: UNKNOWN
Classifier: Intended Audience :: Science/Research
Classifier: Topic :: Scientific/Engineering
Classifier: License :: OSI Approved :: GNU General Public License v3 or later (GPLv3+)
Requires-Dist: numpy
Requires-Dist: scipy
Requires-Dist: scikit-image
Requires-Dist: aotools
Requires-Dist: six
Requires-Dist: sympy
